planer_store/__init__.py
planer_store/cellpose/__init__.py
planer_store/cellpose/main.py
planer_store/crnn_ocr/__init__.py
planer_store/crnn_ocr/main.py
planer_store/face_68_key/__init__.py
planer_store/face_68_key/main.py
planer_store/hed_edge/__init__.py
planer_store/hed_edge/main.py
planer_store/obj_recognize/__init__.py
planer_store/obj_recognize/main.py
planer_store/super_resolution/__init__.py
planer_store/super_resolution/main.py
planer_store-0.11.dist-info/LICENSE
planer_store-0.11.dist-info/METADATA
planer_store-0.11.dist-info/WHEEL
planer_store-0.11.dist-info/top_level.txt
planer_store-0.11.dist-info/RECORD
