Metadata-Version: 2.1
Name: planer-store
Version: 0.11
Summary: toolbox of planer
Home-page: https://github.com/Image-Py/planer-store
Author: Y.Dong, YXDragon
Author-email: yxdragon@imagepy.org
License: BSD 3-clause
Platform: UNKNOWN
Requires-Dist: planer
Requires-Dist: tqdm
